[ { "prim": "UNPAIR" },
  { "prim": "PUSH",
    "args":
      [ { "prim": "string" }, { "string": "FA2_INVALID_OWNER_ACCESS" } ] },
  { "prim": "DUP", "args": [ { "int": "3" } ] }, { "prim": "SENDER" },
  { "prim": "SWAP" }, { "prim": "GET", "args": [ { "int": "3" } ] },
  { "prim": "CAR" }, { "prim": "SWAP" }, { "prim": "COMPARE" },
  { "prim": "EQ" },
  { "prim": "IF",
    "args": [ [ { "prim": "DROP" } ], [ { "prim": "FAILWITH" } ] ] },
  { "prim": "IF_LEFT",
    "args":
      [ [ { "prim": "IF_LEFT",
            "args":
              [ [ { "prim": "SWAP" }, { "prim": "DUP" },
                  { "prim": "GET", "args": [ { "int": "3" } ] },
                  { "prim": "DIG", "args": [ { "int": "2" } ] },
                  { "prim": "SOME" },
                  { "prim": "UPDATE", "args": [ { "int": "3" } ] },
                  { "prim": "UPDATE", "args": [ { "int": "3" } ] } ],
                [ { "prim": "SWAP" },
                  { "prim": "EMPTY_BIG_MAP",
                    "args": [ { "prim": "string" }, { "prim": "bytes" } ] },
                  { "prim": "UPDATE", "args": [ { "int": "1" } ] },
                  { "prim": "SWAP" },
                  { "prim": "ITER",
                    "args":
                      [ [ { "prim": "UNPAIR" },
                          { "prim": "DUP", "args": [ { "int": "3" } ] },
                          { "prim": "DIG", "args": [ { "int": "3" } ] },
                          { "prim": "CAR" },
                          { "prim": "DIG", "args": [ { "int": "3" } ] },
                          { "prim": "DIG", "args": [ { "int": "3" } ] },
                          { "prim": "SWAP" }, { "prim": "SOME" },
                          { "prim": "SWAP" }, { "prim": "UPDATE" },
                          { "prim": "UPDATE", "args": [ { "int": "1" } ] } ] ] } ] ] } ],
        [ { "prim": "IF_LEFT",
            "args":
              [ [ { "prim": "ITER",
                    "args":
                      [ [ { "prim": "IF_LEFT",
                            "args":
                              [ [ { "prim": "DUP" }, { "prim": "CAR" },
                                  { "prim": "IF_LEFT",
                                    "args":
                                      [ [ { "prim": "IF_LEFT",
                                            "args":
                                              [ [ { "prim": "IF_LEFT",
                                                    "args":
                                                      [ [ { "prim": "DROP" },
                                                          { "prim": "DUP" },
                                                          { "prim": "CDR" },
                                                          { "prim":
                                                              "CONTRACT",
                                                            "args":
                                                              [ { "prim":
                                                                    "pair",
                                                                  "args":
                                                                    [ { "prim":
                                                                    "address",
                                                                    "annots":
                                                                    [ "%owner" ] },
                                                                    { "prim":
                                                                    "nat",
                                                                    "annots":
                                                                    [ "%token_id" ] },
                                                                    { "prim":
                                                                    "nat",
                                                                    "annots":
                                                                    [ "%amount" ] } ] } ],
                                                            "annots":
                                                              [ "%burn_hook" ] },
                                                          { "prim": "IF_NONE",
                                                            "args":
                                                              [ [ { "prim":
                                                                    "PUSH",
                                                                    "args":
                                                                    [ { "prim":
                                                                    "string" },
                                                                    { "string":
                                                                    "FA_BURN_HOOK_UNDEFINED" } ] },
                                                                  { "prim":
                                                                    "FAILWITH" } ],
                                                                [ { "prim":
                                                                    "DROP" } ] ] },
                                                          { "prim": "DUP",
                                                            "args":
                                                              [ { "int": "2" } ] },
                                                          { "prim": "DUP",
                                                            "args":
                                                              [ { "int": "3" } ] },
                                                          { "prim": "GET",
                                                            "args":
                                                              [ { "int": "5" } ] },
                                                          { "prim": "DIG",
                                                            "args":
                                                              [ { "int": "3" } ] },
                                                          { "prim": "GET",
                                                            "args":
                                                              [ { "int": "5" } ] },
                                                          { "prim": "GET",
                                                            "args":
                                                              [ { "int": "7" } ] },
                                                          { "prim": "DIG",
                                                            "args":
                                                              [ { "int": "3" } ] },
                                                          { "prim": "CDR" },
                                                          { "prim": "PUSH",
                                                            "args":
                                                              [ { "prim":
                                                                    "bool" },
                                                                { "prim":
                                                                    "True" } ] },
                                                          { "prim": "SWAP" },
                                                          { "prim": "UPDATE" },
                                                          { "prim": "UPDATE",
                                                            "args":
                                                              [ { "int": "7" } ] },
                                                          { "prim": "UPDATE",
                                                            "args":
                                                              [ { "int": "5" } ] } ],
                                                        [ { "prim": "DROP" },
                                                          { "prim": "DUP" },
                                                          { "prim": "CDR" },
                                                          { "prim":
                                                              "CONTRACT",
                                                            "args":
                                                              [ { "prim":
                                                                    "pair",
                                                                  "args":
                                                                    [ { "prim":
                                                                    "pair",
                                                                    "args":
                                                                    [ { "prim":
                                                                    "nat",
                                                                    "annots":
                                                                    [ "%token_id" ] },
                                                                    { "prim":
                                                                    "map",
                                                                    "args":
                                                                    [ { "prim":
                                                                    "string" },
                                                                    { "prim":
                                                                    "bytes" } ],
                                                                    "annots":
                                                                    [ "%token_info" ] } ],
                                                                    "annots":
                                                                    [ "%token_metadata" ] },
                                                                    { "prim":
                                                                    "pair",
                                                                    "args":
                                                                    [ { "prim":
                                                                    "nat",
                                                                    "annots":
                                                                    [ "%total_shares" ] },
                                                                    { "prim":
                                                                    "map",
                                                                    "args":
                                                                    [ { "prim":
                                                                    "address" },
                                                                    { "prim":
                                                                    "nat" } ],
                                                                    "annots":
                                                                    [ "%shares" ] } ],
                                                                    "annots":
                                                                    [ "%royalties" ] },
                                                                    { "prim":
                                                                    "nat",
                                                                    "annots":
                                                                    [ "%max_supply" ] } ] } ],
                                                            "annots":
                                                              [ "%create_hook" ] },
                                                          { "prim": "IF_NONE",
                                                            "args":
                                                              [ [ { "prim":
                                                                    "PUSH",
                                                                    "args":
                                                                    [ { "prim":
                                                                    "string" },
                                                                    { "string":
                                                                    "FA_CREATE_HOOK_UNDEFINED" } ] },
                                                                  { "prim":
                                                                    "FAILWITH" } ],
                                                                [ { "prim":
                                                                    "DROP" } ] ] },
                                                          { "prim": "DUP",
                                                            "args":
                                                              [ { "int": "2" } ] },
                                                          { "prim": "DUP",
                                                            "args":
                                                              [ { "int": "3" } ] },
                                                          { "prim": "GET",
                                                            "args":
                                                              [ { "int": "5" } ] },
                                                          { "prim": "DIG",
                                                            "args":
                                                              [ { "int": "3" } ] },
                                                          { "prim": "GET",
                                                            "args":
                                                              [ { "int": "5" } ] },
                                                          { "prim": "GET",
                                                            "args":
                                                              [ { "int": "3" } ] },
                                                          { "prim": "DIG",
                                                            "args":
                                                              [ { "int": "3" } ] },
                                                          { "prim": "CDR" },
                                                          { "prim": "PUSH",
                                                            "args":
                                                              [ { "prim":
                                                                    "bool" },
                                                                { "prim":
                                                                    "True" } ] },
                                                          { "prim": "SWAP" },
                                                          { "prim": "UPDATE" },
                                                          { "prim": "UPDATE",
                                                            "args":
                                                              [ { "int": "3" } ] },
                                                          { "prim": "UPDATE",
                                                            "args":
                                                              [ { "int": "5" } ] } ] ] } ],
                                                [ { "prim": "IF_LEFT",
                                                    "args":
                                                      [ [ { "prim": "DROP" },
                                                          { "prim": "DUP" },
                                                          { "prim": "CDR" },
                                                          { "prim":
                                                              "CONTRACT",
                                                            "args":
                                                              [ { "prim":
                                                                    "map",
                                                                  "args":
                                                                    [ { "prim":
                                                                    "nat" },
                                                                    { "prim":
                                                                    "pair",
                                                                    "args":
                                                                    [ { "prim":
                                                                    "nat",
                                                                    "annots":
                                                                    [ "%token_id" ] },
                                                                    { "prim":
                                                                    "map",
                                                                    "args":
                                                                    [ { "prim":
                                                                    "string" },
                                                                    { "prim":
                                                                    "bytes" } ],
                                                                    "annots":
                                                                    [ "%token_info" ] } ] } ] } ],
                                                            "annots":
                                                              [ "%update_metadata_hook" ] },
                                                          { "prim": "IF_NONE",
                                                            "args":
                                                              [ [ { "prim":
                                                                    "PUSH",
                                                                    "args":
                                                                    [ { "prim":
                                                                    "string" },
                                                                    { "string":
                                                                    "FA_UPDATE_METADATA_HOOK_UNDEFINED" } ] },
                                                                  { "prim":
                                                                    "FAILWITH" } ],
                                                                [ { "prim":
                                                                    "DROP" } ] ] },
                                                          { "prim": "DUP",
                                                            "args":
                                                              [ { "int": "2" } ] },
                                                          { "prim": "DUP",
                                                            "args":
                                                              [ { "int": "3" } ] },
                                                          { "prim": "GET",
                                                            "args":
                                                              [ { "int": "5" } ] },
                                                          { "prim": "DIG",
                                                            "args":
                                                              [ { "int": "3" } ] },
                                                          { "prim": "GET",
                                                            "args":
                                                              [ { "int": "5" } ] },
                                                          { "prim": "GET",
                                                            "args":
                                                              [ { "int": "8" } ] },
                                                          { "prim": "DIG",
                                                            "args":
                                                              [ { "int": "3" } ] },
                                                          { "prim": "CDR" },
                                                          { "prim": "PUSH",
                                                            "args":
                                                              [ { "prim":
                                                                    "bool" },
                                                                { "prim":
                                                                    "True" } ] },
                                                          { "prim": "SWAP" },
                                                          { "prim": "UPDATE" },
                                                          { "prim": "UPDATE",
                                                            "args":
                                                              [ { "int": "8" } ] },
                                                          { "prim": "UPDATE",
                                                            "args":
                                                              [ { "int": "5" } ] } ],
                                                        [ { "prim": "DROP" },
                                                          { "prim": "DUP" },
                                                          { "prim": "CDR" },
                                                          { "prim":
                                                              "CONTRACT",
                                                            "args":
                                                              [ { "prim":
                                                                    "pair",
                                                                  "args":
                                                                    [ { "prim":
                                                                    "address",
                                                                    "annots":
                                                                    [ "%owner" ] },
                                                                    { "prim":
                                                                    "nat",
                                                                    "annots":
                                                                    [ "%token_id" ] },
                                                                    { "prim":
                                                                    "nat",
                                                                    "annots":
                                                                    [ "%amount" ] } ] } ],
                                                            "annots":
                                                              [ "%mint_hook" ] },
                                                          { "prim": "IF_NONE",
                                                            "args":
                                                              [ [ { "prim":
                                                                    "PUSH",
                                                                    "args":
                                                                    [ { "prim":
                                                                    "string" },
                                                                    { "string":
                                                                    "FA_MINT_HOOK_UNDEFINED" } ] },
                                                                  { "prim":
                                                                    "FAILWITH" } ],
                                                                [ { "prim":
                                                                    "DROP" } ] ] },
                                                          { "prim": "DUP",
                                                            "args":
                                                              [ { "int": "2" } ] },
                                                          { "prim": "DUP",
                                                            "args":
                                                              [ { "int": "3" } ] },
                                                          { "prim": "GET",
                                                            "args":
                                                              [ { "int": "5" } ] },
                                                          { "prim": "DIG",
                                                            "args":
                                                              [ { "int": "3" } ] },
                                                          { "prim": "GET",
                                                            "args":
                                                              [ { "int": "5" } ] },
                                                          { "prim": "GET",
                                                            "args":
                                                              [ { "int": "5" } ] },
                                                          { "prim": "DIG",
                                                            "args":
                                                              [ { "int": "3" } ] },
                                                          { "prim": "CDR" },
                                                          { "prim": "PUSH",
                                                            "args":
                                                              [ { "prim":
                                                                    "bool" },
                                                                { "prim":
                                                                    "True" } ] },
                                                          { "prim": "SWAP" },
                                                          { "prim": "UPDATE" },
                                                          { "prim": "UPDATE",
                                                            "args":
                                                              [ { "int": "5" } ] },
                                                          { "prim": "UPDATE",
                                                            "args":
                                                              [ { "int": "5" } ] } ] ] } ] ] } ],
                                        [ { "prim": "DROP" },
                                          { "prim": "DUP" },
                                          { "prim": "CDR" },
                                          { "prim": "CONTRACT",
                                            "args":
                                              [ { "prim": "list",
                                                  "args":
                                                    [ { "prim": "pair",
                                                        "args":
                                                          [ { "prim":
                                                                "address",
                                                              "annots":
                                                                [ "%from_" ] },
                                                            { "prim": "list",
                                                              "args":
                                                                [ { "prim":
                                                                    "pair",
                                                                    "args":
                                                                    [ { "prim":
                                                                    "address",
                                                                    "annots":
                                                                    [ "%to_" ] },
                                                                    { "prim":
                                                                    "nat",
                                                                    "annots":
                                                                    [ "%token_id" ] },
                                                                    { "prim":
                                                                    "nat",
                                                                    "annots":
                                                                    [ "%amount" ] } ] } ],
                                                              "annots":
                                                                [ "%txs" ] } ] } ] } ],
                                            "annots": [ "%transfer_hook" ] },
                                          { "prim": "IF_NONE",
                                            "args":
                                              [ [ { "prim": "PUSH",
                                                    "args":
                                                      [ { "prim": "string" },
                                                        { "string":
                                                            "FA_TRANSFER_HOOK_UNDEFINED" } ] },
                                                  { "prim": "FAILWITH" } ],
                                                [ { "prim": "DROP" } ] ] },
                                          { "prim": "DUP",
                                            "args": [ { "int": "2" } ] },
                                          { "prim": "DUP",
                                            "args": [ { "int": "3" } ] },
                                          { "prim": "GET",
                                            "args": [ { "int": "5" } ] },
                                          { "prim": "DIG",
                                            "args": [ { "int": "3" } ] },
                                          { "prim": "GET",
                                            "args": [ { "int": "5" } ] },
                                          { "prim": "CAR" },
                                          { "prim": "DIG",
                                            "args": [ { "int": "3" } ] },
                                          { "prim": "CDR" },
                                          { "prim": "PUSH",
                                            "args":
                                              [ { "prim": "bool" },
                                                { "prim": "True" } ] },
                                          { "prim": "SWAP" },
                                          { "prim": "UPDATE" },
                                          { "prim": "UPDATE",
                                            "args": [ { "int": "1" } ] },
                                          { "prim": "UPDATE",
                                            "args": [ { "int": "5" } ] } ] ] } ],
                                [ { "prim": "DUP" }, { "prim": "CAR" },
                                  { "prim": "IF_LEFT",
                                    "args":
                                      [ [ { "prim": "IF_LEFT",
                                            "args":
                                              [ [ { "prim": "IF_LEFT",
                                                    "args":
                                                      [ [ { "prim": "DROP" },
                                                          { "prim": "DUP",
                                                            "args":
                                                              [ { "int": "2" } ] },
                                                          { "prim": "DUP",
                                                            "args":
                                                              [ { "int": "3" } ] },
                                                          { "prim": "GET",
                                                            "args":
                                                              [ { "int": "5" } ] },
                                                          { "prim": "DIG",
                                                            "args":
                                                              [ { "int": "3" } ] },
                                                          { "prim": "GET",
                                                            "args":
                                                              [ { "int": "5" } ] },
                                                          { "prim": "GET",
                                                            "args":
                                                              [ { "int": "7" } ] },
                                                          { "prim": "DIG",
                                                            "args":
                                                              [ { "int": "3" } ] },
                                                          { "prim": "CDR" },
                                                          { "prim": "PUSH",
                                                            "args":
                                                              [ { "prim":
                                                                    "bool" },
                                                                { "prim":
                                                                    "False" } ] },
                                                          { "prim": "SWAP" },
                                                          { "prim": "UPDATE" },
                                                          { "prim": "UPDATE",
                                                            "args":
                                                              [ { "int": "7" } ] },
                                                          { "prim": "UPDATE",
                                                            "args":
                                                              [ { "int": "5" } ] } ],
                                                        [ { "prim": "DROP" },
                                                          { "prim": "DUP",
                                                            "args":
                                                              [ { "int": "2" } ] },
                                                          { "prim": "DUP",
                                                            "args":
                                                              [ { "int": "3" } ] },
                                                          { "prim": "GET",
                                                            "args":
                                                              [ { "int": "5" } ] },
                                                          { "prim": "DIG",
                                                            "args":
                                                              [ { "int": "3" } ] },
                                                          { "prim": "GET",
                                                            "args":
                                                              [ { "int": "5" } ] },
                                                          { "prim": "GET",
                                                            "args":
                                                              [ { "int": "3" } ] },
                                                          { "prim": "DIG",
                                                            "args":
                                                              [ { "int": "3" } ] },
                                                          { "prim": "CDR" },
                                                          { "prim": "PUSH",
                                                            "args":
                                                              [ { "prim":
                                                                    "bool" },
                                                                { "prim":
                                                                    "False" } ] },
                                                          { "prim": "SWAP" },
                                                          { "prim": "UPDATE" },
                                                          { "prim": "UPDATE",
                                                            "args":
                                                              [ { "int": "3" } ] },
                                                          { "prim": "UPDATE",
                                                            "args":
                                                              [ { "int": "5" } ] } ] ] } ],
                                                [ { "prim": "IF_LEFT",
                                                    "args":
                                                      [ [ { "prim": "DROP" },
                                                          { "prim": "DUP",
                                                            "args":
                                                              [ { "int": "2" } ] },
                                                          { "prim": "DUP",
                                                            "args":
                                                              [ { "int": "3" } ] },
                                                          { "prim": "GET",
                                                            "args":
                                                              [ { "int": "5" } ] },
                                                          { "prim": "DIG",
                                                            "args":
                                                              [ { "int": "3" } ] },
                                                          { "prim": "GET",
                                                            "args":
                                                              [ { "int": "5" } ] },
                                                          { "prim": "GET",
                                                            "args":
                                                              [ { "int": "8" } ] },
                                                          { "prim": "DIG",
                                                            "args":
                                                              [ { "int": "3" } ] },
                                                          { "prim": "CDR" },
                                                          { "prim": "PUSH",
                                                            "args":
                                                              [ { "prim":
                                                                    "bool" },
                                                                { "prim":
                                                                    "False" } ] },
                                                          { "prim": "SWAP" },
                                                          { "prim": "UPDATE" },
                                                          { "prim": "UPDATE",
                                                            "args":
                                                              [ { "int": "8" } ] },
                                                          { "prim": "UPDATE",
                                                            "args":
                                                              [ { "int": "5" } ] } ],
                                                        [ { "prim": "DROP" },
                                                          { "prim": "DUP",
                                                            "args":
                                                              [ { "int": "2" } ] },
                                                          { "prim": "DUP",
                                                            "args":
                                                              [ { "int": "3" } ] },
                                                          { "prim": "GET",
                                                            "args":
                                                              [ { "int": "5" } ] },
                                                          { "prim": "DIG",
                                                            "args":
                                                              [ { "int": "3" } ] },
                                                          { "prim": "GET",
                                                            "args":
                                                              [ { "int": "5" } ] },
                                                          { "prim": "GET",
                                                            "args":
                                                              [ { "int": "5" } ] },
                                                          { "prim": "DIG",
                                                            "args":
                                                              [ { "int": "3" } ] },
                                                          { "prim": "CDR" },
                                                          { "prim": "PUSH",
                                                            "args":
                                                              [ { "prim":
                                                                    "bool" },
                                                                { "prim":
                                                                    "False" } ] },
                                                          { "prim": "SWAP" },
                                                          { "prim": "UPDATE" },
                                                          { "prim": "UPDATE",
                                                            "args":
                                                              [ { "int": "5" } ] },
                                                          { "prim": "UPDATE",
                                                            "args":
                                                              [ { "int": "5" } ] } ] ] } ] ] } ],
                                        [ { "prim": "DROP" },
                                          { "prim": "DUP",
                                            "args": [ { "int": "2" } ] },
                                          { "prim": "DUP",
                                            "args": [ { "int": "3" } ] },
                                          { "prim": "GET",
                                            "args": [ { "int": "5" } ] },
                                          { "prim": "DIG",
                                            "args": [ { "int": "3" } ] },
                                          { "prim": "GET",
                                            "args": [ { "int": "5" } ] },
                                          { "prim": "CAR" },
                                          { "prim": "DIG",
                                            "args": [ { "int": "3" } ] },
                                          { "prim": "CDR" },
                                          { "prim": "PUSH",
                                            "args":
                                              [ { "prim": "bool" },
                                                { "prim": "False" } ] },
                                          { "prim": "SWAP" },
                                          { "prim": "UPDATE" },
                                          { "prim": "UPDATE",
                                            "args": [ { "int": "1" } ] },
                                          { "prim": "UPDATE",
                                            "args": [ { "int": "5" } ] } ] ] } ] ] } ] ] } ],
                [ { "prim": "ITER",
                    "args":
                      [ [ { "prim": "IF_LEFT",
                            "args":
                              [ [ { "prim": "DUP" }, { "prim": "CAR" },
                                  { "prim": "IF_LEFT",
                                    "args":
                                      [ [ { "prim": "IF_LEFT",
                                            "args":
                                              [ [ { "prim": "DROP" },
                                                  { "prim": "DUP",
                                                    "args":
                                                      [ { "int": "2" } ] },
                                                  { "prim": "DUP",
                                                    "args":
                                                      [ { "int": "3" } ] },
                                                  { "prim": "GET",
                                                    "args":
                                                      [ { "int": "3" } ] },
                                                  { "prim": "DIG",
                                                    "args":
                                                      [ { "int": "3" } ] },
                                                  { "prim": "GET",
                                                    "args":
                                                      [ { "int": "3" } ] },
                                                  { "prim": "GET",
                                                    "args":
                                                      [ { "int": "5" } ] },
                                                  { "prim": "DIG",
                                                    "args":
                                                      [ { "int": "3" } ] },
                                                  { "prim": "CDR" },
                                                  { "prim": "PUSH",
                                                    "args":
                                                      [ { "prim": "bool" },
                                                        { "prim": "True" } ] },
                                                  { "prim": "SWAP" },
                                                  { "prim": "UPDATE" },
                                                  { "prim": "UPDATE",
                                                    "args":
                                                      [ { "int": "5" } ] },
                                                  { "prim": "UPDATE",
                                                    "args":
                                                      [ { "int": "3" } ] } ],
                                                [ { "prim": "DROP" },
                                                  { "prim": "DUP",
                                                    "args":
                                                      [ { "int": "2" } ] },
                                                  { "prim": "DUP",
                                                    "args":
                                                      [ { "int": "3" } ] },
                                                  { "prim": "GET",
                                                    "args":
                                                      [ { "int": "3" } ] },
                                                  { "prim": "DIG",
                                                    "args":
                                                      [ { "int": "3" } ] },
                                                  { "prim": "GET",
                                                    "args":
                                                      [ { "int": "3" } ] },
                                                  { "prim": "GET",
                                                    "args":
                                                      [ { "int": "9" } ] },
                                                  { "prim": "DIG",
                                                    "args":
                                                      [ { "int": "3" } ] },
                                                  { "prim": "CDR" },
                                                  { "prim": "PUSH",
                                                    "args":
                                                      [ { "prim": "bool" },
                                                        { "prim": "True" } ] },
                                                  { "prim": "SWAP" },
                                                  { "prim": "UPDATE" },
                                                  { "prim": "UPDATE",
                                                    "args":
                                                      [ { "int": "9" } ] },
                                                  { "prim": "UPDATE",
                                                    "args":
                                                      [ { "int": "3" } ] } ] ] } ],
                                        [ { "prim": "IF_LEFT",
                                            "args":
                                              [ [ { "prim": "DROP" },
                                                  { "prim": "DUP",
                                                    "args":
                                                      [ { "int": "2" } ] },
                                                  { "prim": "DUP",
                                                    "args":
                                                      [ { "int": "3" } ] },
                                                  { "prim": "GET",
                                                    "args":
                                                      [ { "int": "3" } ] },
                                                  { "prim": "DIG",
                                                    "args":
                                                      [ { "int": "3" } ] },
                                                  { "prim": "GET",
                                                    "args":
                                                      [ { "int": "3" } ] },
                                                  { "prim": "GET",
                                                    "args":
                                                      [ { "int": "7" } ] },
                                                  { "prim": "DIG",
                                                    "args":
                                                      [ { "int": "3" } ] },
                                                  { "prim": "CDR" },
                                                  { "prim": "PUSH",
                                                    "args":
                                                      [ { "prim": "bool" },
                                                        { "prim": "True" } ] },
                                                  { "prim": "SWAP" },
                                                  { "prim": "UPDATE" },
                                                  { "prim": "UPDATE",
                                                    "args":
                                                      [ { "int": "7" } ] },
                                                  { "prim": "UPDATE",
                                                    "args":
                                                      [ { "int": "3" } ] } ],
                                                [ { "prim": "DROP" },
                                                  { "prim": "DUP",
                                                    "args":
                                                      [ { "int": "2" } ] },
                                                  { "prim": "DUP",
                                                    "args":
                                                      [ { "int": "3" } ] },
                                                  { "prim": "GET",
                                                    "args":
                                                      [ { "int": "3" } ] },
                                                  { "prim": "DIG",
                                                    "args":
                                                      [ { "int": "3" } ] },
                                                  { "prim": "GET",
                                                    "args":
                                                      [ { "int": "3" } ] },
                                                  { "prim": "GET",
                                                    "args":
                                                      [ { "int": "10" } ] },
                                                  { "prim": "DIG",
                                                    "args":
                                                      [ { "int": "3" } ] },
                                                  { "prim": "CDR" },
                                                  { "prim": "PUSH",
                                                    "args":
                                                      [ { "prim": "bool" },
                                                        { "prim": "True" } ] },
                                                  { "prim": "SWAP" },
                                                  { "prim": "UPDATE" },
                                                  { "prim": "UPDATE",
                                                    "args":
                                                      [ { "int": "10" } ] },
                                                  { "prim": "UPDATE",
                                                    "args":
                                                      [ { "int": "3" } ] } ] ] } ] ] } ],
                                [ { "prim": "DUP" }, { "prim": "CAR" },
                                  { "prim": "IF_LEFT",
                                    "args":
                                      [ [ { "prim": "IF_LEFT",
                                            "args":
                                              [ [ { "prim": "DROP" },
                                                  { "prim": "DUP",
                                                    "args":
                                                      [ { "int": "2" } ] },
                                                  { "prim": "DUP",
                                                    "args":
                                                      [ { "int": "3" } ] },
                                                  { "prim": "GET",
                                                    "args":
                                                      [ { "int": "3" } ] },
                                                  { "prim": "DIG",
                                                    "args":
                                                      [ { "int": "3" } ] },
                                                  { "prim": "GET",
                                                    "args":
                                                      [ { "int": "3" } ] },
                                                  { "prim": "GET",
                                                    "args":
                                                      [ { "int": "5" } ] },
                                                  { "prim": "DIG",
                                                    "args":
                                                      [ { "int": "3" } ] },
                                                  { "prim": "CDR" },
                                                  { "prim": "PUSH",
                                                    "args":
                                                      [ { "prim": "bool" },
                                                        { "prim": "False" } ] },
                                                  { "prim": "SWAP" },
                                                  { "prim": "UPDATE" },
                                                  { "prim": "UPDATE",
                                                    "args":
                                                      [ { "int": "5" } ] },
                                                  { "prim": "UPDATE",
                                                    "args":
                                                      [ { "int": "3" } ] } ],
                                                [ { "prim": "DROP" },
                                                  { "prim": "DUP",
                                                    "args":
                                                      [ { "int": "2" } ] },
                                                  { "prim": "DUP",
                                                    "args":
                                                      [ { "int": "3" } ] },
                                                  { "prim": "GET",
                                                    "args":
                                                      [ { "int": "3" } ] },
                                                  { "prim": "DIG",
                                                    "args":
                                                      [ { "int": "3" } ] },
                                                  { "prim": "GET",
                                                    "args":
                                                      [ { "int": "3" } ] },
                                                  { "prim": "GET",
                                                    "args":
                                                      [ { "int": "9" } ] },
                                                  { "prim": "DIG",
                                                    "args":
                                                      [ { "int": "3" } ] },
                                                  { "prim": "CDR" },
                                                  { "prim": "PUSH",
                                                    "args":
                                                      [ { "prim": "bool" },
                                                        { "prim": "False" } ] },
                                                  { "prim": "SWAP" },
                                                  { "prim": "UPDATE" },
                                                  { "prim": "UPDATE",
                                                    "args":
                                                      [ { "int": "9" } ] },
                                                  { "prim": "UPDATE",
                                                    "args":
                                                      [ { "int": "3" } ] } ] ] } ],
                                        [ { "prim": "IF_LEFT",
                                            "args":
                                              [ [ { "prim": "DROP" },
                                                  { "prim": "DUP",
                                                    "args":
                                                      [ { "int": "2" } ] },
                                                  { "prim": "DUP",
                                                    "args":
                                                      [ { "int": "3" } ] },
                                                  { "prim": "GET",
                                                    "args":
                                                      [ { "int": "3" } ] },
                                                  { "prim": "DIG",
                                                    "args":
                                                      [ { "int": "3" } ] },
                                                  { "prim": "GET",
                                                    "args":
                                                      [ { "int": "3" } ] },
                                                  { "prim": "GET",
                                                    "args":
                                                      [ { "int": "7" } ] },
                                                  { "prim": "DIG",
                                                    "args":
                                                      [ { "int": "3" } ] },
                                                  { "prim": "CDR" },
                                                  { "prim": "PUSH",
                                                    "args":
                                                      [ { "prim": "bool" },
                                                        { "prim": "False" } ] },
                                                  { "prim": "SWAP" },
                                                  { "prim": "UPDATE" },
                                                  { "prim": "UPDATE",
                                                    "args":
                                                      [ { "int": "7" } ] },
                                                  { "prim": "UPDATE",
                                                    "args":
                                                      [ { "int": "3" } ] } ],
                                                [ { "prim": "DROP" },
                                                  { "prim": "DUP",
                                                    "args":
                                                      [ { "int": "2" } ] },
                                                  { "prim": "DUP",
                                                    "args":
                                                      [ { "int": "3" } ] },
                                                  { "prim": "GET",
                                                    "args":
                                                      [ { "int": "3" } ] },
                                                  { "prim": "DIG",
                                                    "args":
                                                      [ { "int": "3" } ] },
                                                  { "prim": "GET",
                                                    "args":
                                                      [ { "int": "3" } ] },
                                                  { "prim": "GET",
                                                    "args":
                                                      [ { "int": "10" } ] },
                                                  { "prim": "DIG",
                                                    "args":
                                                      [ { "int": "3" } ] },
                                                  { "prim": "CDR" },
                                                  { "prim": "PUSH",
                                                    "args":
                                                      [ { "prim": "bool" },
                                                        { "prim": "False" } ] },
                                                  { "prim": "SWAP" },
                                                  { "prim": "UPDATE" },
                                                  { "prim": "UPDATE",
                                                    "args":
                                                      [ { "int": "10" } ] },
                                                  { "prim": "UPDATE",
                                                    "args":
                                                      [ { "int": "3" } ] } ] ] } ] ] } ] ] } ] ] } ] ] } ] ] },
  { "prim": "NIL", "args": [ { "prim": "operation" } ] },
  { "prim": "PAIR" } ]

